tsutil/__init__.py
tsutil/daemonize.py
tsutil/decorators.py
tsutil/encoder.py
tsutil/http_server.py
tsutil/sequence.py
tsutil/sorted.py
tsutil/sync.py
tsutil/util.py
tsutil-0.1.8.4.dist-info/LICENSE
tsutil-0.1.8.4.dist-info/METADATA
tsutil-0.1.8.4.dist-info/WHEEL
tsutil-0.1.8.4.dist-info/top_level.txt
tsutil-0.1.8.4.dist-info/RECORD
