Metadata-Version: 2.1
Name: tsutil
Version: 0.1.8.4
Summary: my python tool module
Home-page: http://github.com/turbidsoul/tsutil
Author: Turbidsoul Chen
Author-email: sccn.sq+py@gmail.com
License: MIT
Platform: UNKNOWN
License-File: LICENSE
Requires-Dist: requests (==2.23.0)
